gator/api/client/__init__.py
gator/api/client/helpers.py
gator_client-0.3.0.dist-info/METADATA
gator_client-0.3.0.dist-info/WHEEL
gator_client-0.3.0.dist-info/LICENSE
gator_client-0.3.0.dist-info/RECORD
