Metadata-Version: 2.1
Name: gator-client
Version: 0.3.0
Summary: A web client for the Gator API
License: MIT
Author: Shon Verch
Author-email: verchshon@gmail.com
Requires-Python: >=3.9,<4.0
Classifier: License :: OSI Approved :: MIT License
Classifier: Programming Language :: Python :: 3
Classifier: Programming Language :: Python :: 3.9
Classifier: Programming Language :: Python :: 3.10
Classifier: Programming Language :: Python :: 3.11
Requires-Dist: certifi (>=2022.6.15,<2023.0.0)
Requires-Dist: gator-core (>=1.1.4,<2.0.0)
Requires-Dist: urllib3 (>=1.26.9,<2.0.0)
